etcd_sdk_python-0.0.7.dist-info/licenses/AUTHORS.rst
etcd_sdk_python-0.0.7.dist-info/licenses/LICENSE
pyetcd/__init__.py
pyetcd/client.py
pyetcd/events.py
pyetcd/exceptions.py
pyetcd/leases.py
pyetcd/locks.py
pyetcd/members.py
pyetcd/transactions.py
pyetcd/utils.py
pyetcd/watch.py
pyetcd/etcdrpc/__init__.py
pyetcd/etcdrpc/auth_pb2.py
pyetcd/etcdrpc/auth_pb2.pyi
pyetcd/etcdrpc/kv_pb2.py
pyetcd/etcdrpc/kv_pb2.pyi
pyetcd/etcdrpc/rpc_pb2.py
pyetcd/etcdrpc/rpc_pb2.pyi
pyetcd/etcdrpc/rpc_pb2_grpc.py
pyetcd/proto/auth.proto
pyetcd/proto/kv.proto
pyetcd/proto/rpc.proto
etcd_sdk_python-0.0.7.dist-info/METADATA
etcd_sdk_python-0.0.7.dist-info/WHEEL
etcd_sdk_python-0.0.7.dist-info/top_level.txt
etcd_sdk_python-0.0.7.dist-info/RECORD
