Metadata-Version: 2.4
Name: etcd-sdk-python
Version: 0.0.7
Summary: Python client for the etcd v3 API for python >= 3.8
Author-email: XuanYang-cn <jumpthepig@gmail.com>
Project-URL: Homepage, https://github.com/XuanYang-cn/pyetcd
Project-URL: Docs: User Guide, https://pyetcd-docs.readthedocs.io/en/latest/
Project-URL: Source Code, https://github.com/XuanYang-cn/pyetcd
Classifier: Programming Language :: Python :: 3
Classifier: License :: OSI Approved :: Apache Software License
Classifier: Operating System :: OS Independent
Requires-Python: >=3.8
License-File: LICENSE
License-File: AUTHORS.rst
Requires-Dist: grpcio<=2,>=1.66.2
Provides-Extra: dev
Requires-Dist: build; extra == "dev"
Requires-Dist: PyYAML; extra == "dev"
Requires-Dist: bumpversion; extra == "dev"
Requires-Dist: coverage; extra == "dev"
Requires-Dist: flake8-import-order; extra == "dev"
Requires-Dist: flake8; extra == "dev"
Requires-Dist: flake8-docstrings; extra == "dev"
Requires-Dist: hypothesis; extra == "dev"
Requires-Dist: pytest; extra == "dev"
Requires-Dist: pytest-cov; extra == "dev"
Requires-Dist: mock; extra == "dev"
Requires-Dist: pifpaf; extra == "dev"
Requires-Dist: tenacity; extra == "dev"
Requires-Dist: grpcio-tools==1.66.2; extra == "dev"
Requires-Dist: ruff; extra == "dev"
Provides-Extra: docs
Requires-Dist: m2r; extra == "docs"
Requires-Dist: Sphinx>=5.3.0; extra == "docs"
Requires-Dist: sphinx-copybutton; extra == "docs"
Requires-Dist: sphinx-rtd-theme; extra == "docs"
Requires-Dist: sphinxcontrib-applehelp; extra == "docs"
Requires-Dist: sphinxcontrib-devhelp; extra == "docs"
Requires-Dist: sphinxcontrib-htmlhelp; extra == "docs"
Requires-Dist: sphinxcontrib-jsmath; extra == "docs"
Requires-Dist: sphinxcontrib-qthelp; extra == "docs"
Requires-Dist: sphinxcontrib-serializinghtml; extra == "docs"
Requires-Dist: sphinxcontrib-prettyspecialmethods; extra == "docs"
Dynamic: license-file
